config_checker/__init__.py
config_checker/config_checker.py
rig_remote/__init__.py
rig_remote/app_config.py
rig_remote/bookmarksmanager.py
rig_remote/constants.py
rig_remote/disk_io.py
rig_remote/exceptions.py
rig_remote/queue_comms.py
rig_remote/rig_remote.py
rig_remote/rigctl.py
rig_remote/scanning.py
rig_remote/stmessenger.py
rig_remote/syncing.py
rig_remote/ui.py
rig_remote/utility.py
rig_remote/models/__init__.py
rig_remote/models/bookmark.py
rig_remote/models/channel.py
rig_remote/models/modulation_modes.py
rig_remote/models/rig_endpoint.py
rig_remote/models/scanning_task.py
rig_remote/models/sync_task.py
rig_remote-3.0.dist-info/licenses/LICENSE
rig_remote-3.0.dist-info/METADATA
rig_remote-3.0.dist-info/WHEEL
rig_remote-3.0.dist-info/entry_points.txt
rig_remote-3.0.dist-info/top_level.txt
rig_remote-3.0.dist-info/RECORD
