Metadata-Version: 2.4
Name: rig-remote
Version: 3.0
Summary: A tool for remotely control a radio transceiver using RigCtl protocol over TCP/IP. Rig Remote provides frequency scanning and monitoring, frequency bookmarks.
Home-page: https://github.com/Marzona/rig-remote/
Download-URL: https://github.com/Marzona/rig-remote/releases
Author: Simone Marzona
Author-email: Simone Marzona <marzona@knoway.info>
Maintainer-email: Simone Marzona <marzona@knoway.info>
License-Expression: MIT
Project-URL: Homepage, https://github.com/Marzona/rig-remote
Project-URL: Issues, https://github.com/Marzona/rig-remote/issues
Keywords: rigctl,ham,radio,bookmarks,scanner
Classifier: Programming Language :: Python
Classifier: Topic :: Communications
Classifier: Development Status :: 4 - Beta
Classifier: Intended Audience :: Information Technology
Requires-Python: >=3.13
License-File: LICENSE
Requires-Dist: setuptools==80.8.0
Requires-Dist: datetime==5.5
Requires-Dist: logging==0.4.9.6
Requires-Dist: astroid==3.3.6
Requires-Dist: configparser==7.1.0
Requires-Dist: coverage==7.6.9
Requires-Dist: dill==0.3.9
Requires-Dist: execnet==2.1.1
Requires-Dist: iniconfig==2.0.0
Requires-Dist: isort==5.13.2
Requires-Dist: mccabe==0.7.0
Requires-Dist: mock==5.1.0
Requires-Dist: mypy==1.13.0
Requires-Dist: mypy-extensions==1.0.0
Requires-Dist: packaging==24.2
Requires-Dist: platformdirs==4.3.6
Requires-Dist: pluggy==1.5.0
Requires-Dist: pylint==3.3.2
Requires-Dist: pytest==8.3.4
Requires-Dist: pytest-cov==6.0.0
Requires-Dist: pytest-xdist==3.6.1
Requires-Dist: pytz==2025.2
Requires-Dist: ruff==0.8.4
Requires-Dist: tomlkit==0.13.2
Requires-Dist: typing-extensions==4.12.2
Requires-Dist: zope-interface==7.2
Dynamic: author
Dynamic: download-url
Dynamic: home-page
Dynamic: license-file
